wxwidgets/__init__.py
wxwidgets/_directory_input.py
wxwidgets/_file_input.py
wxwidgets/_input_widget.py
wxwidgets/_preview.py
wxwidgets/_simple_button.py
wxwidgets/_simple_input.py
wxwidgets/_simple_sizer.py
wxwidgets/gui.py
wxwidgets-1.0.5.dist-info/METADATA
wxwidgets-1.0.5.dist-info/WHEEL
wxwidgets-1.0.5.dist-info/top_level.txt
wxwidgets-1.0.5.dist-info/RECORD
