Metadata-Version: 2.1
Name: wxwidgets
Version: 1.0.5
Summary: wxpython based gui elements
Home-page: https://github.com/ChsHub/wxwidgets
Author: ChsHub
License: MIT License
Platform: UNKNOWN
Classifier: Programming Language :: Python :: 3
Requires-Dist: wxPython
Requires-Dist: webcolors
